{
    "tech": [
        {
            "name": "java",
            "pro": "stat1",
            "con": "bad"
        },
        {
            "name": "javascript",
            "pro": "stat2",
            "con": "stat1"
        },
        {
            "name": "javax",
            "pro": "stat1",
            "con": "bad"
        },
        {
            "name": "typescript",
            "pro": "stat8",
            "con": "horrible"
        },
        {
            "name": "python",
            "pro": "bad",
            "con": "stat5"
        }
    ]
}